<?xml version="1.0" encoding="utf-8" ?>
<Patch>
		<Operation Class="PatchOperationSequence">
			<operations>
				<li Class="PatchOperationRemove">
					<xpath>Defs/ThingDef[
					defName="CGF1_MWP_L6_WOMBAT_M8C_"
					]/comps/li[@Class = "MVCF.Comps.CompProperties_VerbProps"]</xpath>
					</li>
			
				<li Class="PatchOperationReplace">
					<xpath>
						/Defs/ThingDef[
							defName = "CGF1_MWP_LAW_80_" or
							defName = "CGF1_MWP_Shorts_Blowpipe_" or
							defName = "CGF1_MWP_L6_WOMBAT_" or
							defName = "CGF1_MWP_L6_WOMBAT_M8C_" or
							defName = "CGF1_MWP_Vickers_Vigilant_"
						]/tools
					</xpath>
						<value>
							<tools>
							  <li Class="CombatExtended.ToolCE">
								<label>barrel</label>
								<capacities>
								  <li>Blunt</li>
								</capacities>
								<power>10</power>
								<cooldownTime>2.44</cooldownTime>
								<armorPenetrationBlunt>3.5</armorPenetrationBlunt>
								<linkedBodyPartsGroup>Barrel</linkedBodyPartsGroup>
							  </li>
						</tools>
					</value>
				</li>
				
				<li Class="CombatExtended.PatchOperationMakeGunCECompatible">
					<defName>CGF1_MWP_LAW_80_</defName>
					<statBases>
                        <SightsEfficiency>1.00</SightsEfficiency>
                        <ShotSpread>0.20</ShotSpread>
                        <SwayFactor>2.27</SwayFactor>
                        <Bulk>17.00</Bulk>
						<Mass>9</Mass>
						<RangedWeapon_Cooldown>1.50</RangedWeapon_Cooldown>
					</statBases>
					<Properties>
							<verbClass>CombatExtended.Verb_ShootCEOneUse</verbClass>
							<hasStandardCommand>true</hasStandardCommand>
							<defaultProjectile>Bullet_94mm_LAW80_</defaultProjectile>
							<warmupTime>1.9</warmupTime>
							<range>25</range>
							<ai_AvoidFriendlyFireRadius>3</ai_AvoidFriendlyFireRadius>
							<minRange>2</minRange>
							<soundCast>CGF1_MWP_SFX_Launcher_LAW</soundCast>
							<soundCastTail>GunTail_Heavy</soundCastTail>
							<muzzleFlashScale>14</muzzleFlashScale>
							<stopBurstWithoutLos>false</stopBurstWithoutLos>
							<ai_IsBuildingDestroyer>true</ai_IsBuildingDestroyer>
							<targetParams>
								<canTargetLocations>true</canTargetLocations>
						    </targetParams>
							<recoilAmount>2.93</recoilAmount>
                    </Properties>
					<FireModes>
						<aiUseBurstMode>FALSE</aiUseBurstMode>
						<aiAimMode>AimedShot</aiAimMode>
					</FireModes>
					<weaponTags>
						<li>CE_AI_AOE</li>
					</weaponTags>
					<AllowWithRunAndGun>false</AllowWithRunAndGun>
				</li>
				<li Class="CombatExtended.PatchOperationMakeGunCECompatible">
					<defName>CGF1_MWP_Shorts_Blowpipe_</defName>
					<statBases>
                        <SightsEfficiency>1.00</SightsEfficiency>
                        <ShotSpread>0.20</ShotSpread>
                        <SwayFactor>2.27</SwayFactor>
                        <Bulk>30.00</Bulk>
						<Mass>22</Mass>
						<RangedWeapon_Cooldown>2.50</RangedWeapon_Cooldown>
					</statBases>
					<Properties>
							<verbClass>CombatExtended.Verb_ShootCE</verbClass>
							<hasStandardCommand>true</hasStandardCommand>
							<defaultProjectile>Bullet_76mmBlowpipe_Frag</defaultProjectile>
							<warmupTime>5</warmupTime>
							<range>50.9</range>
							<ai_AvoidFriendlyFireRadius>3</ai_AvoidFriendlyFireRadius>
							<minRange>3</minRange>
							<soundCast>CGF1_MWP_SFX_Launcher_Javelin</soundCast>
							<soundCastTail>GunTail_Heavy</soundCastTail>
							<soundAiming>CGF1_MWP_SFX_Launcher_LockOn</soundAiming>
							<muzzleFlashScale>14</muzzleFlashScale>
							<stopBurstWithoutLos>false</stopBurstWithoutLos>
							<ai_IsBuildingDestroyer>true</ai_IsBuildingDestroyer>
							<onlyManualCast>true</onlyManualCast>
							<targetParams>
								<canTargetBuildings>true</canTargetBuildings>
								<canTargetLocations>true</canTargetLocations>
								<canTargetPawns>false</canTargetPawns>
								<canTargetAnimals>false</canTargetAnimals>
								<canTargetHumans>false</canTargetHumans>
								<canTargetMechs>false</canTargetMechs>
						    </targetParams>
							<recoilAmount>3.50</recoilAmount>
                     </Properties>
					 <AmmoUser>
						<magazineSize>1</magazineSize>
						<reloadTime>12</reloadTime>
						<ammoSet>AmmoSet_76mmBlowpipe</ammoSet>
					</AmmoUser>
					<FireModes>
						<aiUseBurstMode>FALSE</aiUseBurstMode>
						<aiAimMode>AimedShot</aiAimMode>
					</FireModes>
					<weaponTags>
						<li>CE_AI_AOE</li>
					</weaponTags>
					<AllowWithRunAndGun>false</AllowWithRunAndGun>
				</li>
				<li Class="CombatExtended.PatchOperationMakeGunCECompatible">
					<defName>CGF1_MWP_Vickers_Vigilant_</defName>
					<statBases>
                        <SightsEfficiency>1.00</SightsEfficiency>
                        <ShotSpread>0.02</ShotSpread>
                        <SwayFactor>2.0</SwayFactor>
                        <Bulk>25.55</Bulk>
						<Mass>16</Mass>
						<RangedWeapon_Cooldown>1.50</RangedWeapon_Cooldown>
					</statBases>
					<Properties>
							<verbClass>CombatExtended.Verb_ShootCE</verbClass>
							<hasStandardCommand>true</hasStandardCommand>
							<defaultProjectile>Bullet_120mmVigilant_HEAT</defaultProjectile>
							<warmupTime>5</warmupTime>
							<range>100</range>
							<ai_AvoidFriendlyFireRadius>3</ai_AvoidFriendlyFireRadius>
							<minRange>6</minRange>
							<soundCast>CGF1_MWP_SFX_Launcher_AA</soundCast>
							<soundAiming>CGF1_MWP_SFX_Launcher_LockOn</soundAiming>
							<soundCastTail>GunTail_Heavy</soundCastTail>
							<muzzleFlashScale>16</muzzleFlashScale>
							<stopBurstWithoutLos>false</stopBurstWithoutLos>
							<ai_IsBuildingDestroyer>true</ai_IsBuildingDestroyer>
							<targetParams>
								<canTargetBuildings>true</canTargetBuildings>
								<canTargetLocations>true</canTargetLocations>
						    </targetParams>
							<recoilPattern>Mounted</recoilPattern>
							<recoilAmount>2.93</recoilAmount>
                     </Properties>
					<AmmoUser>
						<magazineSize>1</magazineSize>
						<reloadTime>9.9</reloadTime>
						<ammoSet>AmmoSet_120mmVigilant</ammoSet>
					</AmmoUser>
					<FireModes>
						<aiUseBurstMode>FALSE</aiUseBurstMode>
						<aiAimMode>AimedShot</aiAimMode>
					</FireModes>
					<weaponTags>
						<li>CE_AI_AOE</li>
					</weaponTags>
					<AllowWithRunAndGun>false</AllowWithRunAndGun>
				</li>
				<li Class="CombatExtended.PatchOperationMakeGunCECompatible">
					<defName>CGF1_MWP_L6_WOMBAT_</defName>
					<statBases>
                        <SightsEfficiency>1.50</SightsEfficiency>
                        <ShotSpread>0.05</ShotSpread>
                        <SwayFactor>2.0</SwayFactor>
                        <Bulk>32.00</Bulk>
						<Mass>50</Mass>
						<RangedWeapon_Cooldown>1.50</RangedWeapon_Cooldown>
					</statBases>
					<Properties>
							<verbClass>CombatExtended.Verb_ShootCE</verbClass>
							<hasStandardCommand>true</hasStandardCommand>
							<defaultProjectile>Bullet_120mmBATShell_HEAT</defaultProjectile>
							<warmupTime>5</warmupTime>
							<range>80</range>
							<ai_AvoidFriendlyFireRadius>3</ai_AvoidFriendlyFireRadius>
							<minRange>6</minRange>
							<soundCast>CGF1_MWP_SFX_Autocannon1</soundCast>
							<soundCastTail>GunTail_Heavy</soundCastTail>
							<muzzleFlashScale>16</muzzleFlashScale>
							<stopBurstWithoutLos>false</stopBurstWithoutLos>
							<ai_IsBuildingDestroyer>true</ai_IsBuildingDestroyer>
							<targetParams>
								<canTargetBuildings>true</canTargetBuildings>
								<canTargetLocations>true</canTargetLocations>
						    </targetParams>
							<recoilPattern>Mounted</recoilPattern>
							<recoilAmount>2.93</recoilAmount>
                     </Properties>
					<AmmoUser>
						<magazineSize>1</magazineSize>
						<reloadTime>9.9</reloadTime>
						<ammoSet>AmmoSet_120mmBATShell</ammoSet>
					</AmmoUser>
					<FireModes>
						<aiUseBurstMode>FALSE</aiUseBurstMode>
						<aiAimMode>AimedShot</aiAimMode>
					</FireModes>
					<weaponTags>
						<li>CE_AI_AOE</li>
					</weaponTags>
					<AllowWithRunAndGun>false</AllowWithRunAndGun>
				</li>
				<li Class="CombatExtended.PatchOperationMakeGunCECompatible">
					<defName>CGF1_MWP_L6_WOMBAT_M8C_</defName>
					<statBases>
                        <SightsEfficiency>1.50</SightsEfficiency>
                        <ShotSpread>0.05</ShotSpread>
                        <SwayFactor>2.0</SwayFactor>
                        <Bulk>34.00</Bulk>
						<Mass>55.5</Mass>
						<RangedWeapon_Cooldown>1.50</RangedWeapon_Cooldown>
					</statBases>
					<Properties>
							<verbClass>CombatExtended.Verb_ShootCE</verbClass>
							<hasStandardCommand>true</hasStandardCommand>
							<defaultProjectile>Bullet_120mmBATShell_HEAT</defaultProjectile>
							<warmupTime>5</warmupTime>
							<range>80</range>
							<ai_AvoidFriendlyFireRadius>3</ai_AvoidFriendlyFireRadius>
							<minRange>6</minRange>
							<soundCast>CGF1_MWP_SFX_Autocannon1</soundCast>
							<soundCastTail>GunTail_Heavy</soundCastTail>
							<muzzleFlashScale>16</muzzleFlashScale>
							<stopBurstWithoutLos>false</stopBurstWithoutLos>
							<ai_IsBuildingDestroyer>true</ai_IsBuildingDestroyer>
							<targetParams>
								<canTargetBuildings>true</canTargetBuildings>
								<canTargetLocations>true</canTargetLocations>
						    </targetParams>
							<recoilPattern>Mounted</recoilPattern>
							<recoilAmount>2.93</recoilAmount>
                     </Properties>
					<AmmoUser>
						<magazineSize>1</magazineSize>
						<reloadTime>9.9</reloadTime>
						<ammoSet>AmmoSet_120mmBATShell</ammoSet>
					</AmmoUser>
					<FireModes>
						<aiUseBurstMode>FALSE</aiUseBurstMode>
						<aiAimMode>AimedShot</aiAimMode>
					</FireModes>
					<weaponTags>
						<li>CE_AI_AOE</li>
					</weaponTags>
					<AllowWithRunAndGun>false</AllowWithRunAndGun>
				</li>
				
				<li Class="PatchOperationAdd">
					<xpath>
						/Defs/ThingDef[
							defName = "CGF1_MWP_L6_WOMBAT_M8C_"
						]/comps
					</xpath>
					<value>
						<li Class="CombatExtended.CompProperties_UnderBarrel">
						  <propsUnderBarrel>
							<magazineSize>5</magazineSize>
							<reloadTime>4</reloadTime>
							<ammoSet>AmmoSet_127x77mm</ammoSet>
						  </propsUnderBarrel>
						  <verbPropsUnderBarrel>
							<recoilAmount>1.75</recoilAmount>
							<verbClass>CombatExtended.Verb_ShootCE</verbClass>
							<hasStandardCommand>true</hasStandardCommand>
							<defaultProjectile>Bullet_127x77mm_FMJ</defaultProjectile>
							<warmupTime>3</warmupTime>
							<range>80</range>
							<targetParams>
								<canTargetLocations>true</canTargetLocations>
							</targetParams>
							<soundCast>CGF1_MWP_SFX_MG_Light4</soundCast>
							<soundCastTail>GunTail_Medium</soundCastTail>
							<muzzleFlashScale>5</muzzleFlashScale>
						  </verbPropsUnderBarrel>
						  <propsFireModesUnderBarrel>
							<aiUseBurstMode>FALSE</aiUseBurstMode>
							<aiAimMode>AimedShot</aiAimMode>
							<aimedBurstShotCount>1</aimedBurstShotCount>
						  </propsFireModesUnderBarrel>
					  </li>  
					</value>
				</li>

			</operations>
	</Operation>

</Patch>