<?xml version="1.0" encoding="utf-8" ?>
<Patch>
		<Operation Class="PatchOperationSequence">
			<operations>
			
				<li Class="PatchOperationReplace">
					<xpath>
						/Defs/ThingDef[
							defName = "CGF1_MWP_Bren_280_" or
							defName = "CGF1_MWP_Bren_L4A1" or
							defName = "CGF1_MWP_Bren_L4A2_" or
							defName = "CGF1_MWP_Bren_L4A3_" or
							defName = "CGF1_MWP_Bren_L4A4_" or
							defName = "CGF1_MWP_L7A1_" or
							defName = "CGF1_MWP_L8A1_" or
							defName = "CGF1_MWP_L37A1_" or
							defName = "CGF1_MWP_L43A1_RangingGun_" or
							defName = "CGF1_MWP_Stoner_63_LMG_485mm_" or
							defName = "CGF1_MWP_X11E2_TADEN_" or
							defName = "CGF1_MWP_X11E2_TADEN_Mounted_" or
							defName = "CGF1_MWP_X11E3_" or
							defName = "CGF1_MWP_X11E4_"
						]/tools
					</xpath>
					<value>
						<tools>
							<li Class="CombatExtended.ToolCE">
								<label>stock</label>
								<capacities>
									<li>Blunt</li>
								</capacities>
								<power>8</power>
								<cooldownTime>1.55</cooldownTime>
								<chanceFactor>1.5</chanceFactor>
								<armorPenetrationBlunt>2.755</armorPenetrationBlunt>
								<linkedBodyPartsGroup>Stock</linkedBodyPartsGroup>
							</li>
							<li Class="CombatExtended.ToolCE">
								<label>barrel</label>
								<capacities>
									<li>Blunt</li>
								</capacities>
								<power>5</power>
								<cooldownTime>2.02</cooldownTime>
								<armorPenetrationBlunt>1.630</armorPenetrationBlunt>
								<linkedBodyPartsGroup>Barrel</linkedBodyPartsGroup>
							</li>
							<li Class="CombatExtended.ToolCE">
								<label>muzzle</label>
								<capacities>
									<li>Poke</li>
								</capacities>
								<power>8</power>
								<cooldownTime>1.55</cooldownTime>
								<armorPenetrationBlunt>2.755</armorPenetrationBlunt>
								<linkedBodyPartsGroup>Muzzle</linkedBodyPartsGroup>
							</li>
						</tools>
					</value>
				</li>
				
				<li Class="CombatExtended.PatchOperationMakeGunCECompatible">
					<defName>CGF1_MWP_Bren_280_</defName>
					<statBases>
                        <SightsEfficiency>1.00</SightsEfficiency>
                        <ShotSpread>0.06</ShotSpread>
                        <SwayFactor>1.53</SwayFactor>
                        <Bulk>14.00</Bulk>
						<Mass>9.8</Mass>
						<RangedWeapon_Cooldown>0.56</RangedWeapon_Cooldown>
					</statBases>
					<Properties>
                           <verbClass>CombatExtended.Verb_ShootCE</verbClass>
                           <hasStandardCommand>true</hasStandardCommand>
                           <defaultProjectile>Bullet_280British_FMJ</defaultProjectile>
                           <warmupTime>1.2</warmupTime>
                           <range>75</range>
						   <ticksBetweenBurstShots>7</ticksBetweenBurstShots>
						   <burstShotCount>10</burstShotCount>
                           <soundCast>CGF1_MWP_SFX_MG_Medium3</soundCast>
                           <soundCastTail>GunTail_Medium</soundCastTail>
                           <muzzleFlashScale>9</muzzleFlashScale>
						   <recoilAmount>1.30</recoilAmount>
                     </Properties>
					 <AmmoUser>
						<magazineSize>30</magazineSize>
						<reloadTime>4</reloadTime>
						<ammoSet>AmmoSet_280British</ammoSet>
					</AmmoUser>
					<FireModes>
						<aimedBurstShotCount>5</aimedBurstShotCount>
						<aiUseBurstMode>FALSE</aiUseBurstMode>
                        <aiAimMode>SuppressFire</aiAimMode>
					</FireModes>
					<weaponTags>
						<li>CE_MachineGun</li>
						<li>CE_AI_LMG</li>
						<li>Bipod_LMG</li>
					</weaponTags>
				</li>
				<li Class="CombatExtended.PatchOperationMakeGunCECompatible">
					<defName>CGF1_MWP_Bren_L4A1_</defName>
					<statBases>
                        <SightsEfficiency>1.00</SightsEfficiency>
                        <ShotSpread>0.06</ShotSpread>
                        <SwayFactor>1.50</SwayFactor>
                        <Bulk>14.50</Bulk>
						<Mass>10.1</Mass>
						<RangedWeapon_Cooldown>0.56</RangedWeapon_Cooldown>
					</statBases>
					<Properties>
                           <verbClass>CombatExtended.Verb_ShootCE</verbClass>
                           <hasStandardCommand>true</hasStandardCommand>
                           <defaultProjectile>Bullet_762x51mmNATO_FMJ</defaultProjectile>
                           <warmupTime>1.2</warmupTime>
                           <range>75</range>
						   <ticksBetweenBurstShots>6</ticksBetweenBurstShots>
						   <burstShotCount>10</burstShotCount>
                           <soundCast>CGF1_MWP_SFX_MG_Medium3</soundCast>
                           <soundCastTail>GunTail_Medium</soundCastTail>
                           <muzzleFlashScale>9</muzzleFlashScale>
						   <recoilAmount>1.32</recoilAmount>
                     </Properties>
					 <AmmoUser>
						<magazineSize>30</magazineSize>
						<reloadTime>4</reloadTime>
						<ammoSet>AmmoSet_762x51mmNATO</ammoSet>
					</AmmoUser>
					<FireModes>
						<aimedBurstShotCount>5</aimedBurstShotCount>
						<aiUseBurstMode>FALSE</aiUseBurstMode>
                        <aiAimMode>SuppressFire</aiAimMode>
					</FireModes>
					<weaponTags>
						<li>CE_MachineGun</li>
						<li>CE_AI_LMG</li>
						<li>Bipod_LMG</li>
					</weaponTags>
				</li>
				<li Class="CombatExtended.PatchOperationMakeGunCECompatible">
					<defName>CGF1_MWP_Bren_L4A2_</defName>
					<statBases>
                        <SightsEfficiency>1.00</SightsEfficiency>
                        <ShotSpread>0.06</ShotSpread>
                        <SwayFactor>1.53</SwayFactor>
                        <Bulk>14.00</Bulk>
						<Mass>9.8</Mass>
						<RangedWeapon_Cooldown>0.56</RangedWeapon_Cooldown>
					</statBases>
					<Properties>
                           <verbClass>CombatExtended.Verb_ShootCE</verbClass>
                           <hasStandardCommand>true</hasStandardCommand>
                           <defaultProjectile>Bullet_762x51mmNATO_FMJ</defaultProjectile>
                           <warmupTime>1.2</warmupTime>
                           <range>75</range>
						   <ticksBetweenBurstShots>6</ticksBetweenBurstShots>
						   <burstShotCount>10</burstShotCount>
                           <soundCast>CGF1_MWP_SFX_MG_Medium3</soundCast>
                           <soundCastTail>GunTail_Medium</soundCastTail>
                           <muzzleFlashScale>9</muzzleFlashScale>
						   <recoilAmount>1.32</recoilAmount>
                     </Properties>
					 <AmmoUser>
						<magazineSize>30</magazineSize>
						<reloadTime>4</reloadTime>
						<ammoSet>AmmoSet_762x51mmNATO</ammoSet>
					</AmmoUser>
					<FireModes>
						<aimedBurstShotCount>5</aimedBurstShotCount>
						<aiUseBurstMode>FALSE</aiUseBurstMode>
                        <aiAimMode>SuppressFire</aiAimMode>
					</FireModes>
					<weaponTags>
						<li>CE_MachineGun</li>
						<li>CE_AI_LMG</li>
						<li>Bipod_LMG</li>
					</weaponTags>
				</li>
				<li Class="CombatExtended.PatchOperationMakeGunCECompatible">
					<defName>CGF1_MWP_Bren_L4A3_</defName>
					<statBases>
                        <SightsEfficiency>1.00</SightsEfficiency>
                        <ShotSpread>0.06</ShotSpread>
                        <SwayFactor>1.50</SwayFactor>
                        <Bulk>14.50</Bulk>
						<Mass>10.1</Mass>
						<RangedWeapon_Cooldown>0.56</RangedWeapon_Cooldown>
					</statBases>
					<Properties>
                           <verbClass>CombatExtended.Verb_ShootCE</verbClass>
                           <hasStandardCommand>true</hasStandardCommand>
                           <defaultProjectile>Bullet_762x51mmNATO_FMJ</defaultProjectile>
                           <warmupTime>1.2</warmupTime>
                           <range>75</range>
						   <ticksBetweenBurstShots>5</ticksBetweenBurstShots>
						   <burstShotCount>10</burstShotCount>
                           <soundCast>CGF1_MWP_SFX_MG_Medium3</soundCast>
                           <soundCastTail>GunTail_Medium</soundCastTail>
                           <muzzleFlashScale>9</muzzleFlashScale>
						   <recoilAmount>1.32</recoilAmount>
                     </Properties>
					 <AmmoUser>
						<magazineSize>30</magazineSize>
						<reloadTime>4</reloadTime>
						<ammoSet>AmmoSet_762x51mmNATO</ammoSet>
					</AmmoUser>
					<FireModes>
						<aimedBurstShotCount>5</aimedBurstShotCount>
						<aiUseBurstMode>FALSE</aiUseBurstMode>
                        <aiAimMode>SuppressFire</aiAimMode>
					</FireModes>
					<weaponTags>
						<li>CE_MachineGun</li>
						<li>CE_AI_LMG</li>
						<li>Bipod_LMG</li>
					</weaponTags>
				</li>
				<li Class="CombatExtended.PatchOperationMakeGunCECompatible">
					<defName>CGF1_MWP_Bren_L4A4_</defName>
					<statBases>
                        <SightsEfficiency>1.00</SightsEfficiency>
                        <ShotSpread>0.06</ShotSpread>
                        <SwayFactor>1.53</SwayFactor>
                        <Bulk>14.00</Bulk>
						<Mass>9.8</Mass>
						<RangedWeapon_Cooldown>0.56</RangedWeapon_Cooldown>
					</statBases>
					<Properties>
                           <verbClass>CombatExtended.Verb_ShootCE</verbClass>
                           <hasStandardCommand>true</hasStandardCommand>
                           <defaultProjectile>Bullet_762x51mmNATO_FMJ</defaultProjectile>
                           <warmupTime>1.2</warmupTime>
                           <range>75</range>
						   <ticksBetweenBurstShots>5</ticksBetweenBurstShots>
						   <burstShotCount>10</burstShotCount>
                           <soundCast>CGF1_MWP_SFX_MG_Medium3</soundCast>
                           <soundCastTail>GunTail_Medium</soundCastTail>
                           <muzzleFlashScale>9</muzzleFlashScale>
						   <recoilAmount>1.32</recoilAmount>
                     </Properties>
					 <AmmoUser>
						<magazineSize>30</magazineSize>
						<reloadTime>4</reloadTime>
						<ammoSet>AmmoSet_762x51mmNATO</ammoSet>
					</AmmoUser>
					<FireModes>
						<aimedBurstShotCount>5</aimedBurstShotCount>
						<aiUseBurstMode>FALSE</aiUseBurstMode>
                        <aiAimMode>SuppressFire</aiAimMode>
					</FireModes>
					<weaponTags>
						<li>CE_MachineGun</li>
						<li>CE_AI_LMG</li>
						<li>Bipod_LMG</li>
					</weaponTags>
				</li>
				<li Class="CombatExtended.PatchOperationMakeGunCECompatible">
					<defName>CGF1_MWP_L7A1_</defName>
					<statBases>
                        <SightsEfficiency>1.00</SightsEfficiency>
                        <ShotSpread>0.04</ShotSpread>
                        <SwayFactor>1.71</SwayFactor>
                        <Bulk>15.63</Bulk>
						<Mass>11.80</Mass>
						<RangedWeapon_Cooldown>0.56</RangedWeapon_Cooldown>
					</statBases>
					<Properties>
                           <verbClass>CombatExtended.Verb_ShootCE</verbClass>
                           <hasStandardCommand>true</hasStandardCommand>
                           <defaultProjectile>Bullet_762x51mmNATO_FMJ</defaultProjectile>
                           <warmupTime>1.3</warmupTime>
                           <range>75</range>
						   <ticksBetweenBurstShots>6</ticksBetweenBurstShots>
						   <burstShotCount>10</burstShotCount>
                           <soundCast>CGF1_MWP_SFX_MG_Medium7</soundCast>
                           <soundCastTail>GunTail_Medium</soundCastTail>
                           <muzzleFlashScale>9</muzzleFlashScale>
						   <recoilAmount>1.31</recoilAmount>
                     </Properties>
					 <AmmoUser>
						<magazineSize>100</magazineSize>
						<reloadTime>7.8</reloadTime>
						<ammoSet>AmmoSet_762x51mmNATO</ammoSet>
					</AmmoUser>
					<FireModes>
						<aimedBurstShotCount>5</aimedBurstShotCount>
						<aiUseBurstMode>FALSE</aiUseBurstMode>
                        <aiAimMode>SuppressFire</aiAimMode>
					</FireModes>
					<weaponTags>
						<li>CE_MachineGun</li>
						<li>CE_AI_LMG</li>
						<li>Bipod_LMG</li>
					</weaponTags>
				</li>
				<li Class="CombatExtended.PatchOperationMakeGunCECompatible">
					<defName>CGF1_MWP_L8A1_</defName>
					<statBases>
                        <SightsEfficiency>0.50</SightsEfficiency>
                        <ShotSpread>0.08</ShotSpread>
                        <SwayFactor>1.71</SwayFactor>
                        <Bulk>14.63</Bulk>
						<Mass>9.80</Mass>
						<RangedWeapon_Cooldown>0.56</RangedWeapon_Cooldown>
					</statBases>
					<Properties>
                           <verbClass>CombatExtended.Verb_ShootCE</verbClass>
                           <hasStandardCommand>true</hasStandardCommand>
                           <defaultProjectile>Bullet_762x51mmNATO_FMJ</defaultProjectile>
                           <warmupTime>2.0</warmupTime>
                           <range>75</range>
						   <ticksBetweenBurstShots>6</ticksBetweenBurstShots>
						   <burstShotCount>10</burstShotCount>
                           <soundCast>CGF1_MWP_SFX_MG_Medium7</soundCast>
                           <soundCastTail>GunTail_Medium</soundCastTail>
                           <muzzleFlashScale>9</muzzleFlashScale>
						   <recoilAmount>1.50</recoilAmount>
                     </Properties>
					 <AmmoUser>
						<magazineSize>100</magazineSize>
						<reloadTime>12.8</reloadTime>
						<ammoSet>AmmoSet_762x51mmNATO</ammoSet>
					</AmmoUser>
					<FireModes>
						<aimedBurstShotCount>5</aimedBurstShotCount>
						<aiUseBurstMode>FALSE</aiUseBurstMode>
                        <aiAimMode>SuppressFire</aiAimMode>
					</FireModes>
					<weaponTags>
						<li>CE_MachineGun</li>
						<li>CE_AI_LMG</li>
					</weaponTags>
					<AllowWithRunAndGun>false</AllowWithRunAndGun>
				</li>
				<li Class="CombatExtended.PatchOperationMakeGunCECompatible">
					<defName>CGF1_MWP_L37A1_</defName>
					<statBases>
                        <SightsEfficiency>0.50</SightsEfficiency>
                        <ShotSpread>0.08</ShotSpread>
                        <SwayFactor>1.71</SwayFactor>
                        <Bulk>14.63</Bulk>
						<Mass>9.80</Mass>
						<RangedWeapon_Cooldown>0.56</RangedWeapon_Cooldown>
					</statBases>
					<Properties>
                           <verbClass>CombatExtended.Verb_ShootCE</verbClass>
                           <hasStandardCommand>true</hasStandardCommand>
                           <defaultProjectile>Bullet_762x51mmNATO_FMJ</defaultProjectile>
                           <warmupTime>2.0</warmupTime>
                           <range>75</range>
						   <ticksBetweenBurstShots>6</ticksBetweenBurstShots>
						   <burstShotCount>10</burstShotCount>
                           <soundCast>CGF1_MWP_SFX_MG_Medium7</soundCast>
                           <soundCastTail>GunTail_Medium</soundCastTail>
                           <muzzleFlashScale>9</muzzleFlashScale>
						   <recoilAmount>1.50</recoilAmount>
                     </Properties>
					 <AmmoUser>
						<magazineSize>100</magazineSize>
						<reloadTime>12.8</reloadTime>
						<ammoSet>AmmoSet_762x51mmNATO</ammoSet>
					</AmmoUser>
					<FireModes>
						<aimedBurstShotCount>5</aimedBurstShotCount>
						<aiUseBurstMode>FALSE</aiUseBurstMode>
                        <aiAimMode>SuppressFire</aiAimMode>
					</FireModes>
					<weaponTags>
						<li>CE_MachineGun</li>
						<li>CE_AI_LMG</li>
					</weaponTags>
					<AllowWithRunAndGun>false</AllowWithRunAndGun>
				</li>
				<li Class="CombatExtended.PatchOperationMakeGunCECompatible">
					<defName>CGF1_MWP_L43A1_RangingGun_</defName>
					<statBases>
                        <SightsEfficiency>1.00</SightsEfficiency>
                        <ShotSpread>0.04</ShotSpread>
                        <SwayFactor>1.71</SwayFactor>
                        <Bulk>14.63</Bulk>
						<Mass>9.80</Mass>
						<RangedWeapon_Cooldown>0.56</RangedWeapon_Cooldown>
					</statBases>
					<Properties>
                           <verbClass>CombatExtended.Verb_ShootCE</verbClass>
                           <hasStandardCommand>true</hasStandardCommand>
                           <defaultProjectile>Bullet_762x51mmNATO_FMJ</defaultProjectile>
                           <warmupTime>2.0</warmupTime>
                           <range>75</range>
						   <ticksBetweenBurstShots>6</ticksBetweenBurstShots>
						   <burstShotCount>10</burstShotCount>
                           <soundCast>CGF1_MWP_SFX_MG_Medium7</soundCast>
                           <soundCastTail>GunTail_Medium</soundCastTail>
                           <muzzleFlashScale>9</muzzleFlashScale>
						   <recoilAmount>1.50</recoilAmount>
                     </Properties>
					 <AmmoUser>
						<magazineSize>100</magazineSize>
						<reloadTime>12.8</reloadTime>
						<ammoSet>AmmoSet_762x51mmNATO</ammoSet>
					</AmmoUser>
					<FireModes>
						<aimedBurstShotCount>5</aimedBurstShotCount>
						<aiUseBurstMode>FALSE</aiUseBurstMode>
                        <aiAimMode>SuppressFire</aiAimMode>
					</FireModes>
					<weaponTags>
						<li>CE_MachineGun</li>
						<li>CE_AI_LMG</li>
					</weaponTags>
					<AllowWithRunAndGun>false</AllowWithRunAndGun>
				</li>
				<li Class="CombatExtended.PatchOperationMakeGunCECompatible">
					<defName>CGF1_MWP_Stoner_63_LMG_485mm_</defName>
					<statBases>
                        <SightsEfficiency>1.00</SightsEfficiency>
                        <ShotSpread>0.07</ShotSpread>
                        <SwayFactor>1.27</SwayFactor>
                        <Bulk>12.50</Bulk>
						<Mass>7.60</Mass>
						<RangedWeapon_Cooldown>0.56</RangedWeapon_Cooldown>
					</statBases>
					<Properties>
                           <verbClass>CombatExtended.Verb_ShootCE</verbClass>
                           <hasStandardCommand>true</hasStandardCommand>
                           <defaultProjectile>Bullet_485x49mm_FMJ</defaultProjectile>
                           <warmupTime>1.1</warmupTime>
                           <range>60</range>
						   <ticksBetweenBurstShots>6</ticksBetweenBurstShots>
						   <burstShotCount>10</burstShotCount>
                           <soundCast>CGF1_MWP_SFX_Rifle_Auto1</soundCast>
                           <soundCastTail>GunTail_Medium</soundCastTail>
                           <muzzleFlashScale>9</muzzleFlashScale>
						   <recoilAmount>1.27</recoilAmount>
                     </Properties>
					 <AmmoUser>
						<magazineSize>100</magazineSize>
						<reloadTime>7.8</reloadTime>
						<ammoSet>AmmoSet_485x49mm</ammoSet>
					</AmmoUser>
					<FireModes>
						<aimedBurstShotCount>5</aimedBurstShotCount>
						<aiUseBurstMode>FALSE</aiUseBurstMode>
                        <aiAimMode>SuppressFire</aiAimMode>
					</FireModes>
					<weaponTags>
						<li>CE_MachineGun</li>
						<li>CE_AI_LMG</li>
						<li>Bipod_LMG</li>
					</weaponTags>
				</li>
				<li Class="CombatExtended.PatchOperationMakeGunCECompatible">
					<defName>CGF1_MWP_X11E2_TADEN_</defName>
					<statBases>
                        <SightsEfficiency>1.00</SightsEfficiency>
                        <ShotSpread>0.06</ShotSpread>
                        <SwayFactor>1.53</SwayFactor>
                        <Bulk>15.15</Bulk>
						<Mass>10.55</Mass>
						<RangedWeapon_Cooldown>0.56</RangedWeapon_Cooldown>
					</statBases>
					<Properties>
                           <verbClass>CombatExtended.Verb_ShootCE</verbClass>
                           <hasStandardCommand>true</hasStandardCommand>
                           <defaultProjectile>Bullet_280British_FMJ</defaultProjectile>
                           <warmupTime>1.2</warmupTime>
                           <range>75</range>
						   <ticksBetweenBurstShots>6</ticksBetweenBurstShots>
						   <burstShotCount>10</burstShotCount>
                           <soundCast>CGF1_MWP_SFX_MG_Medium9</soundCast>
                           <soundCastTail>GunTail_Medium</soundCastTail>
                           <muzzleFlashScale>9</muzzleFlashScale>
						   <recoilAmount>1.31</recoilAmount>
                     </Properties>
					 <AmmoUser>
						<magazineSize>100</magazineSize>
						<reloadTime>7.8</reloadTime>
						<ammoSet>AmmoSet_280British</ammoSet>
					</AmmoUser>
					<FireModes>
						<aimedBurstShotCount>5</aimedBurstShotCount>
						<aiUseBurstMode>FALSE</aiUseBurstMode>
                        <aiAimMode>SuppressFire</aiAimMode>
					</FireModes>
					<weaponTags>
						<li>CE_MachineGun</li>
						<li>CE_AI_LMG</li>
						<li>Bipod_LMG</li>
					</weaponTags>
				</li>
				<li Class="CombatExtended.PatchOperationMakeGunCECompatible">
					<defName>CGF1_MWP_X11E2_TADEN_Mounted_</defName>
					<statBases>
                        <SightsEfficiency>0.50</SightsEfficiency>
                        <ShotSpread>0.08</ShotSpread>
                        <SwayFactor>1.53</SwayFactor>
                        <Bulk>18.45</Bulk>
						<Mass>12.99</Mass>
						<RangedWeapon_Cooldown>0.56</RangedWeapon_Cooldown>
					</statBases>
					<Properties>
                           <verbClass>CombatExtended.Verb_ShootCE</verbClass>
                           <hasStandardCommand>true</hasStandardCommand>
                           <defaultProjectile>Bullet_280British_FMJ</defaultProjectile>
                           <warmupTime>2.0</warmupTime>
                           <range>75</range>
						   <ticksBetweenBurstShots>6</ticksBetweenBurstShots>
						   <burstShotCount>10</burstShotCount>
                           <soundCast>CGF1_MWP_SFX_MG_Medium9</soundCast>
                           <soundCastTail>GunTail_Medium</soundCastTail>
                           <muzzleFlashScale>9</muzzleFlashScale>
						   <recoilAmount>1.50</recoilAmount>
                     </Properties>
					 <AmmoUser>
						<magazineSize>100</magazineSize>
						<reloadTime>7.8</reloadTime>
						<ammoSet>AmmoSet_280British</ammoSet>
					</AmmoUser>
					<FireModes>
						<aimedBurstShotCount>5</aimedBurstShotCount>
						<aiUseBurstMode>FALSE</aiUseBurstMode>
                        <aiAimMode>SuppressFire</aiAimMode>
					</FireModes>
					<weaponTags>
						<li>CE_MachineGun</li>
						<li>CE_AI_LMG</li>
						<li>Bipod_LMG</li>
					</weaponTags>
					<AllowWithRunAndGun>false</AllowWithRunAndGun>
				</li>
				<li Class="CombatExtended.PatchOperationMakeGunCECompatible">
					<defName>CGF1_MWP_X11E3_</defName>
					<statBases>
                        <SightsEfficiency>1.00</SightsEfficiency>
                        <ShotSpread>0.06</ShotSpread>
                        <SwayFactor>1.53</SwayFactor>
                        <Bulk>15.64</Bulk>
						<Mass>10.84</Mass>
						<RangedWeapon_Cooldown>0.56</RangedWeapon_Cooldown>
					</statBases>
					<Properties>
                           <verbClass>CombatExtended.Verb_ShootCE</verbClass>
                           <hasStandardCommand>true</hasStandardCommand>
                           <defaultProjectile>Bullet_762x51mmNATO_FMJ</defaultProjectile>
                           <warmupTime>1.2</warmupTime>
                           <range>75</range>
						   <ticksBetweenBurstShots>6</ticksBetweenBurstShots>
						   <burstShotCount>10</burstShotCount>
                           <soundCast>CGF1_MWP_SFX_MG_Medium9</soundCast>
                           <soundCastTail>GunTail_Medium</soundCastTail>
                           <muzzleFlashScale>9</muzzleFlashScale>
						   <recoilAmount>1.31</recoilAmount>
                     </Properties>
					 <AmmoUser>
						<magazineSize>100</magazineSize>
						<reloadTime>7.8</reloadTime>
						<ammoSet>AmmoSet_762x51mmNATO</ammoSet>
					</AmmoUser>
					<FireModes>
						<aimedBurstShotCount>5</aimedBurstShotCount>
						<aiUseBurstMode>FALSE</aiUseBurstMode>
                        <aiAimMode>SuppressFire</aiAimMode>
					</FireModes>
					<weaponTags>
						<li>CE_MachineGun</li>
						<li>CE_AI_LMG</li>
						<li>Bipod_LMG</li>
					</weaponTags>
				</li>
				<li Class="CombatExtended.PatchOperationMakeGunCECompatible">
					<defName>CGF1_MWP_X11E4_</defName>
					<statBases>
                        <SightsEfficiency>1.00</SightsEfficiency>
                        <ShotSpread>0.06</ShotSpread>
                        <SwayFactor>1.53</SwayFactor>
                        <Bulk>15.64</Bulk>
						<Mass>10.80</Mass>
						<RangedWeapon_Cooldown>0.56</RangedWeapon_Cooldown>
					</statBases>
					<Properties>
                           <verbClass>CombatExtended.Verb_ShootCE</verbClass>
                           <hasStandardCommand>true</hasStandardCommand>
                           <defaultProjectile>Bullet_762x51mmNATO_FMJ</defaultProjectile>
                           <warmupTime>1.2</warmupTime>
                           <range>75</range>
						   <ticksBetweenBurstShots>6</ticksBetweenBurstShots>
						   <burstShotCount>10</burstShotCount>
                           <soundCast>CGF1_MWP_SFX_MG_Medium9</soundCast>
                           <soundCastTail>GunTail_Medium</soundCastTail>
                           <muzzleFlashScale>9</muzzleFlashScale>
						   <recoilAmount>1.31</recoilAmount>
                     </Properties>
					 <AmmoUser>
						<magazineSize>100</magazineSize>
						<reloadTime>7.8</reloadTime>
						<ammoSet>AmmoSet_762x51mmNATO</ammoSet>
					</AmmoUser>
					<FireModes>
						<aimedBurstShotCount>5</aimedBurstShotCount>
						<aiUseBurstMode>FALSE</aiUseBurstMode>
                        <aiAimMode>SuppressFire</aiAimMode>
					</FireModes>
					<weaponTags>
						<li>CE_MachineGun</li>
						<li>CE_AI_LMG</li>
						<li>Bipod_LMG</li>
					</weaponTags>
				</li>
			</operations>
	</Operation>

</Patch>